AUTHORS.md
COPYING
MANIFEST.in
README.rst
setup.py
doc/Makefile
doc/make.bat
doc/source/basic_concepts.rst
doc/source/builtin_drivers.rst
doc/source/changelog.rst
doc/source/conf.py
doc/source/examples.rst
doc/source/index.rst
doc/source/installation.rst
doc/source/logging.rst
doc/source/quickstart.rst
doc/source/slave.rst
doc/source/_static/layers.pdf
doc/source/_static/layers.svg
slave/__init__.py
slave/driver.py
slave/iec60488.py
slave/misc.py
slave/protocol.py
slave/transport.py
slave/types.py
slave.egg-info/PKG-INFO
slave.egg-info/SOURCES.txt
slave.egg-info/dependency_links.txt
slave.egg-info/requires.txt
slave.egg-info/top_level.txt
slave/cryomagnetics/__init__.py
slave/cryomagnetics/mps4g.py
slave/ics/__init__.py
slave/ics/ics4807.py
slave/keithley/__init__.py
slave/keithley/k2182.py
slave/keithley/k6221.py
slave/lakeshore/__init__.py
slave/lakeshore/ls340.py
slave/lakeshore/ls370.py
slave/quantum_design/__init__.py
slave/quantum_design/ppms.py
slave/signal_recovery/__init__.py
slave/signal_recovery/sr5113.py
slave/signal_recovery/sr7225.py
slave/signal_recovery/sr7230.py
slave/srs/__init__.py
slave/srs/sr830.py
slave/srs/sr850.py
slave/test/__init__.py
slave/test/test_cryomagnetics.py
slave/test/test_driver.py
slave/test/test_ics.py
slave/test/test_keithley.py
slave/test/test_lakeshore.py
slave/test/test_misc.py
slave/test/test_protocol.py
slave/test/test_quantum_design.py
slave/test/test_signal_recovery.py
slave/test/test_srs.py
slave/test/test_transport.py
slave/test/test_type.py
slave/vogel/__init__.py
slave/vogel/heps201a.py