Metadata-Version: 1.1
Name: slave
Version: 0.4.0
Summary: A lightweight python package to simplify the communication with several scientific instruments.
Home-page: https://github.com/p3trus/slave
Author: Marco Halder
Author-email: marco.halder@frm2.tum.de
License: GNU General Public License (GPL), Version 3
Platform: UNKNOWN
Classifier: Intended Audience :: Developers
Classifier: Intended Audience :: Science/Research
Classifier: License :: OSI Approved :: GNU General Public License v3 (GPLv3)
Classifier: Operating System :: POSIX :: Linux
Classifier: Programming Language :: Python
Classifier: Programming Language :: Python :: 3
Classifier: Topic :: Communications
Classifier: Topic :: Scientific/Engineering :: Interface Engine/Protocol Translator
Classifier: Topic :: Software Development :: Libraries :: Python Modules
